README.md
setup.cfg
setup.py
minisocket/__init__.py
minisocket/client.py
minisocket/server.py
minisocket/version.py
minisocket.egg-info/PKG-INFO
minisocket.egg-info/SOURCES.txt
minisocket.egg-info/dependency_links.txt
minisocket.egg-info/requires.txt
minisocket.egg-info/top_level.txt
minisocket/lib/__init__.py
minisocket/lib/clientMessage.py
minisocket/lib/serverMessage.py
minisocket/utils/__init__.py
minisocket/utils/io.py
minisocket/utils/ip.py
minisocket/utils/log.py