Metadata-Version: 2.1
Name: minisocket
Version: 0.0.2
Summary: socket api
Home-page: https://github.com/LicharYuan/mini-socket
Author: Liuchun Yuan
Author-email: ylc0003@gmail.com
License: UNKNOWN
Platform: UNKNOWN
Classifier: Programming Language :: Python :: 3
Classifier: License :: OSI Approved :: MIT License
Classifier: Operating System :: OS Independent
Classifier: Development Status :: 3 - Alpha
Classifier: Intended Audience :: Developers
Requires-Python: >=3.6
